[
    {
        "id":1,
        "name":"Revenue",
        "price":390,
        "type":"New",
        "text": "monthly growth",
        "img": "./revenue.png"
    },
    {
        "id":2,
        "name":"Expenses",
        "price":680,
        "type":"Global",
        "text": "monthly growth",
        "img": "./expenses.png"
    },
    {
        "id":3,
        "name":"Expenses",
        "price":680,
        "type":"Intuitive",
        "text": "monthly growth",
        "img": "./expensesIN.png"
    }
]